{"name":"bean","slug":"bean","count":2,"postlist":[{"title":"ConditionalOnMissingBean失效问题追踪","uid":"81d9f9cbb43ffb5d74b9291c7102db6e","slug":"JAVA/ConditionalOnMissingBean失效问题追踪","date":"2024-04-01T18:25:44.000Z","updated":"2025-12-05T01:46:13.482Z","comments":true,"path":"api/articles/JAVA/ConditionalOnMissingBean失效问题追踪.json","keywords":"XuGuangSheng","cover":"/covers/conditionalonmissingbean.jpg","text":"ConditionalOnMissingBean失效问题追踪遇到一个@ConditionalOnMissingBean失效的问题，今天花点时间来分析一下。 现场...","permalink":"/post/JAVA/ConditionalOnMissingBean失效问题追踪","photos":[],"count_time":{"symbolsCount":"7.1k","symbolsTime":"6 mins."},"categories":[{"name":"bean","slug":"bean","count":2,"path":"api/categories/bean.json"},{"name":"JAVA","slug":"bean/JAVA","count":2,"path":"api/categories/bean/JAVA.json"}],"tags":[{"name":"ConditionalOnMissingBean","slug":"ConditionalOnMissingBean","count":1,"path":"api/tags/ConditionalOnMissingBean.json"},{"name":"Configuration","slug":"Configuration","count":1,"path":"api/tags/Configuration.json"},{"name":"RunService","slug":"RunService","count":1,"path":"api/tags/RunService.json"}],"author":{"name":"dandeliono","slug":"blog-author","avatar":"https://avatars.githubusercontent.com/u/29496357","link":"/","description":"永远相信美好的事情即将发生","socials":{"github":"https://github.com/dandeliono","twitter":"","stackoverflow":"","wechat":"","qq":"","weibo":"","zhihu":"","csdn":"","juejin":"","customs":{}}}},{"title":"SpringBoot 扩展接口","uid":"b17fc263eaa274b6bfcba03d60c157eb","slug":"JAVA/SpringBoot 扩展接口","date":"2023-11-15T16:23:04.000Z","updated":"2025-12-05T01:46:36.608Z","comments":true,"path":"api/articles/JAVA/SpringBoot 扩展接口.json","keywords":"XuGuangSheng","cover":"/covers/springboot.jpg","text":"SpringBoot 扩展接口1、背景Spring的核心思想就是容器，当容器refresh的时候，外部看上去风平浪静，其实内部则是一片惊涛骇浪，汪洋一片。Spr...","permalink":"/post/JAVA/SpringBoot 扩展接口","photos":[],"count_time":{"symbolsCount":"15k","symbolsTime":"13 mins."},"categories":[{"name":"bean","slug":"bean","count":2,"path":"api/categories/bean.json"},{"name":"JAVA","slug":"bean/JAVA","count":2,"path":"api/categories/bean/JAVA.json"}],"tags":[{"name":"spring","slug":"spring","count":4,"path":"api/tags/spring.json"},{"name":"org","slug":"org","count":2,"path":"api/tags/org.json"},{"name":"springframework","slug":"springframework","count":1,"path":"api/tags/springframework.json"}],"author":{"name":"dandeliono","slug":"blog-author","avatar":"https://avatars.githubusercontent.com/u/29496357","link":"/","description":"永远相信美好的事情即将发生","socials":{"github":"https://github.com/dandeliono","twitter":"","stackoverflow":"","wechat":"","qq":"","weibo":"","zhihu":"","csdn":"","juejin":"","customs":{}}}}]}