{"name":"OTHER","slug":"OTHER","count":6,"postlist":[{"title":"高校项目汇总","uid":"b7a0ddae62c7a26d383904662692ec9c","slug":"OTHER/高校项目汇总","date":"2025-08-08T16:59:34.000Z","updated":"2025-08-08T09:17:15.621Z","comments":true,"path":"api/articles/OTHER/高校项目汇总.json","keywords":"XuGuangSheng","cover":null,"text":"高校项目汇总【清华大学】 1.学堂在线：https://www.xuetangx.com 2.深言达意：https://www.shenyandayi.com ...","permalink":"/post/OTHER/高校项目汇总","photos":[],"count_time":{"symbolsCount":908,"symbolsTime":"1 mins."},"categories":[{"name":"OTHER","slug":"OTHER","count":6,"path":"api/categories/OTHER.json"}],"tags":[],"author":{"name":"dandeliono","slug":"blog-author","avatar":"https://avatars.githubusercontent.com/u/29496357","link":"/","description":"永远相信美好的事情即将发生","socials":{"github":"https://github.com/dandeliono","twitter":"","stackoverflow":"","wechat":"","qq":"","weibo":"","zhihu":"","csdn":"","juejin":"","customs":{}}}},{"title":"检查网络延时测试 URL 汇总","uid":"2b4f70bb6bf139f87ea4e015f7434bed","slug":"OTHER/检查网络延时测试 URL 汇总","date":"2025-08-08T16:59:34.000Z","updated":"2025-08-08T09:17:15.673Z","comments":true,"path":"api/articles/OTHER/检查网络延时测试 URL 汇总.json","keywords":"XuGuangSheng","cover":null,"text":"检查网络延时测试 URL 汇总 URL 备注 推荐 http://captive.apple.com 苹果设备用于检测 Wi-Fi 是否需要认证登陆的链接 推荐...","permalink":"/post/OTHER/检查网络延时测试 URL 汇总","photos":[],"count_time":{"symbolsCount":"1k","symbolsTime":"1 mins."},"categories":[{"name":"OTHER","slug":"OTHER","count":6,"path":"api/categories/OTHER.json"}],"tags":[],"author":{"name":"dandeliono","slug":"blog-author","avatar":"https://avatars.githubusercontent.com/u/29496357","link":"/","description":"永远相信美好的事情即将发生","socials":{"github":"https://github.com/dandeliono","twitter":"","stackoverflow":"","wechat":"","qq":"","weibo":"","zhihu":"","csdn":"","juejin":"","customs":{}}}},{"title":"小米路由器 AX9000 开发版固件直接获取 SSH","uid":"86b13b8415e2a3ceb3c7a4d2cff47573","slug":"OTHER/小米路由器 AX9000 开发版固件直接获取 SSH","date":"2025-08-08T16:59:34.000Z","updated":"2025-08-08T09:17:15.660Z","comments":true,"path":"api/articles/OTHER/小米路由器 AX9000 开发版固件直接获取 SSH.json","keywords":"XuGuangSheng","cover":[],"text":"小米路由器 AX9000 开发版固件直接获取 SSH1.下载安装开发版固件官网下载: http://www.miwifi.com/miwifi_download...","permalink":"/post/OTHER/小米路由器 AX9000 开发版固件直接获取 SSH","photos":[],"count_time":{"symbolsCount":"1k","symbolsTime":"1 mins."},"categories":[{"name":"OTHER","slug":"OTHER","count":6,"path":"api/categories/OTHER.json"}],"tags":[],"author":{"name":"dandeliono","slug":"blog-author","avatar":"https://avatars.githubusercontent.com/u/29496357","link":"/","description":"永远相信美好的事情即将发生","socials":{"github":"https://github.com/dandeliono","twitter":"","stackoverflow":"","wechat":"","qq":"","weibo":"","zhihu":"","csdn":"","juejin":"","customs":{}}}},{"title":"小米AX9000（SSH后） 开启北京联通IPTV转发服务，全家设备可以看IPTV","uid":"902bce5943bfcf4419fe702bc9520551","slug":"OTHER/小米AX9000（SSH后） 开启北京联通IPTV转发服务，全家设备可以看IPTV","date":"2025-08-08T16:59:34.000Z","updated":"2025-08-08T09:17:15.634Z","comments":true,"path":"api/articles/OTHER/小米AX9000（SSH后） 开启北京联通IPTV转发服务，全家设备可以看IPTV.json","keywords":"XuGuangSheng","cover":null,"text":"小米AX9000（SSH后） 开启北京联通IPTV转发服务，全家设备可以看IPTV北京联通，宽带+IPTV已经入户，我需求不用联通送的IPTV盒子，在一根网线（...","permalink":"/post/OTHER/小米AX9000（SSH后） 开启北京联通IPTV转发服务，全家设备可以看IPTV","photos":[],"count_time":{"symbolsCount":"5.1k","symbolsTime":"5 mins."},"categories":[{"name":"OTHER","slug":"OTHER","count":6,"path":"api/categories/OTHER.json"}],"tags":[],"author":{"name":"dandeliono","slug":"blog-author","avatar":"https://avatars.githubusercontent.com/u/29496357","link":"/","description":"永远相信美好的事情即将发生","socials":{"github":"https://github.com/dandeliono","twitter":"","stackoverflow":"","wechat":"","qq":"","weibo":"","zhihu":"","csdn":"","juejin":"","customs":{}}}},{"title":"Homeassistant - 使用小爱音箱控制 Hass 设备","uid":"0ba37cbc11858729ececbe4090fe5335","slug":"OTHER/Homeassistant - 使用小爱音箱控制 Hass 设备","date":"2025-08-08T16:59:34.000Z","updated":"2025-08-08T09:17:15.647Z","comments":true,"path":"api/articles/OTHER/Homeassistant - 使用小爱音箱控制 Hass 设备.json","keywords":"XuGuangSheng","cover":[],"text":"Homeassistant - 使用小爱音箱控制 Hass 设备使用小爱音箱 + 小爱开放平台技能开发 + NodeRed 控制 Homeassistant 的...","permalink":"/post/OTHER/Homeassistant - 使用小爱音箱控制 Hass 设备","photos":[],"count_time":{"symbolsCount":987,"symbolsTime":"1 mins."},"categories":[{"name":"OTHER","slug":"OTHER","count":6,"path":"api/categories/OTHER.json"}],"tags":[],"author":{"name":"dandeliono","slug":"blog-author","avatar":"https://avatars.githubusercontent.com/u/29496357","link":"/","description":"永远相信美好的事情即将发生","socials":{"github":"https://github.com/dandeliono","twitter":"","stackoverflow":"","wechat":"","qq":"","weibo":"","zhihu":"","csdn":"","juejin":"","customs":{}}}},{"title":"GitHub Actions 入门教程","uid":"f6a976669c665c437623667e8d82197c","slug":"OTHER/GitHub Actions 入门教程","date":"2025-08-08T16:59:34.000Z","updated":"2025-08-08T09:17:15.608Z","comments":true,"path":"api/articles/OTHER/GitHub Actions 入门教程.json","keywords":"XuGuangSheng","cover":[],"text":"GitHub Actions 入门教程前言Github Actions 是 GitHub 推出的持续集成 (Continuous integration，简称 ...","permalink":"/post/OTHER/GitHub Actions 入门教程","photos":[],"count_time":{"symbolsCount":"6.7k","symbolsTime":"6 mins."},"categories":[{"name":"OTHER","slug":"OTHER","count":6,"path":"api/categories/OTHER.json"}],"tags":[],"author":{"name":"dandeliono","slug":"blog-author","avatar":"https://avatars.githubusercontent.com/u/29496357","link":"/","description":"永远相信美好的事情即将发生","socials":{"github":"https://github.com/dandeliono","twitter":"","stackoverflow":"","wechat":"","qq":"","weibo":"","zhihu":"","csdn":"","juejin":"","customs":{}}}}]}