{"total":170,"pageSize":12,"pageCount":15,"data":[{"title":"向量数据库","uid":"98948a6b47eff1c83e919c4c7211acdc","slug":"MIDDLEWARE/向量数据库","date":"2025-08-08T16:59:34.000Z","updated":"2025-08-08T09:17:14.159Z","comments":true,"path":"api/articles/MIDDLEWARE/向量数据库.json","keywords":"XuGuangSheng","cover":[],"text":"向量数据库也许你最近可能听过这样的新闻，某向量数据库的初创公司刚写好 PPT，就获得了几千万的投资，某公司的开源的向量数据库因其代码的简陋而登上了 Hacker...","permalink":"/post/MIDDLEWARE/向量数据库","photos":[],"count_time":{"symbolsCount":"13k","symbolsTime":"12 mins."},"categories":[{"name":"MIDDLEWARE","slug":"MIDDLEWARE","count":38,"path":"api/categories/MIDDLEWARE.json"}],"tags":[],"author":{"name":"dandeliono","slug":"blog-author","avatar":"https://avatars.githubusercontent.com/u/29496357","link":"/","description":"永远相信美好的事情即将发生","socials":{"github":"https://github.com/dandeliono","twitter":"","stackoverflow":"","wechat":"","qq":"","weibo":"","zhihu":"","csdn":"","juejin":"","customs":{}}}},{"title":"如何优雅的升级 Nginx（热部署）版本","uid":"ef5ca056fa60b2d5cee6602c81aa277f","slug":"MIDDLEWARE/如何优雅的升级 Nginx（热部署）版本","date":"2025-08-08T16:59:34.000Z","updated":"2025-08-08T09:17:14.359Z","comments":true,"path":"api/articles/MIDDLEWARE/如何优雅的升级 Nginx（热部署）版本.json","keywords":"XuGuangSheng","cover":null,"text":"如何优雅的升级 Nginx（热部署）版本1. 升级1.1. 下载、编译新版本的 Nginx12345➜ ~ wget https://nginx.org/dow...","permalink":"/post/MIDDLEWARE/如何优雅的升级 Nginx（热部署）版本","photos":[],"count_time":{"symbolsCount":311,"symbolsTime":"1 mins."},"categories":[{"name":"MIDDLEWARE","slug":"MIDDLEWARE","count":38,"path":"api/categories/MIDDLEWARE.json"}],"tags":[],"author":{"name":"dandeliono","slug":"blog-author","avatar":"https://avatars.githubusercontent.com/u/29496357","link":"/","description":"永远相信美好的事情即将发生","socials":{"github":"https://github.com/dandeliono","twitter":"","stackoverflow":"","wechat":"","qq":"","weibo":"","zhihu":"","csdn":"","juejin":"","customs":{}}}},{"title":"我在 Elasticsearch 集群内应该设置多少个分片？","uid":"0a458e361f4a92244bc682099842a8db","slug":"MIDDLEWARE/我在 Elasticsearch 集群内应该设置多少个分片？","date":"2025-08-08T16:59:34.000Z","updated":"2025-08-08T09:17:14.569Z","comments":true,"path":"api/articles/MIDDLEWARE/我在 Elasticsearch 集群内应该设置多少个分片？.json","keywords":"XuGuangSheng","cover":null,"text":"我在 Elasticsearch 集群内应该设置多少个分片？我在 Elasticsearch 集群内应该设置多少个分片？ | Elastic Blog Elas...","permalink":"/post/MIDDLEWARE/我在 Elasticsearch 集群内应该设置多少个分片？","photos":[],"count_time":{"symbolsCount":"4.8k","symbolsTime":"4 mins."},"categories":[{"name":"MIDDLEWARE","slug":"MIDDLEWARE","count":38,"path":"api/categories/MIDDLEWARE.json"}],"tags":[],"author":{"name":"dandeliono","slug":"blog-author","avatar":"https://avatars.githubusercontent.com/u/29496357","link":"/","description":"永远相信美好的事情即将发生","socials":{"github":"https://github.com/dandeliono","twitter":"","stackoverflow":"","wechat":"","qq":"","weibo":"","zhihu":"","csdn":"","juejin":"","customs":{}}}},{"title":"清除信号量队列导致zabbix自动关闭","uid":"262f61f15e8ffbc737e54526fd907a92","slug":"MIDDLEWARE/清除信号量队列导致zabbix自动关闭","date":"2025-08-08T16:59:34.000Z","updated":"2025-08-08T09:17:14.145Z","comments":true,"path":"api/articles/MIDDLEWARE/清除信号量队列导致zabbix自动关闭.json","keywords":"XuGuangSheng","cover":[],"text":"清除信号量队列导致zabbix自动关闭前几天在海外UCloud机器上部署了一套zabbix proxy和zabbix agentd，可是第二天一大早就收到邮件说...","permalink":"/post/MIDDLEWARE/清除信号量队列导致zabbix自动关闭","photos":[],"count_time":{"symbolsCount":"1.2k","symbolsTime":"1 mins."},"categories":[{"name":"MIDDLEWARE","slug":"MIDDLEWARE","count":38,"path":"api/categories/MIDDLEWARE.json"}],"tags":[],"author":{"name":"dandeliono","slug":"blog-author","avatar":"https://avatars.githubusercontent.com/u/29496357","link":"/","description":"永远相信美好的事情即将发生","socials":{"github":"https://github.com/dandeliono","twitter":"","stackoverflow":"","wechat":"","qq":"","weibo":"","zhihu":"","csdn":"","juejin":"","customs":{}}}},{"title":"30张图解： TCP 重传、滑动窗口、流量控制、拥塞控制","uid":"5216b5eeb1a6215d7622123c3d5153cb","slug":"NETWORK/30张图解： TCP 重传、滑动窗口、流量控制、拥塞控制","date":"2025-08-08T16:59:34.000Z","updated":"2025-08-08T09:17:14.120Z","comments":true,"path":"api/articles/NETWORK/30张图解： TCP 重传、滑动窗口、流量控制、拥塞控制.json","keywords":"XuGuangSheng","cover":[],"text":"30张图解： TCP 重传、滑动窗口、流量控制、拥塞控制相信大家都知道 TCP 是一个可靠传输的协议，那它是如何保证可靠的呢？ 为了实现可靠性传输，需要考虑很多...","permalink":"/post/NETWORK/30张图解： TCP 重传、滑动窗口、流量控制、拥塞控制","photos":[],"count_time":{"symbolsCount":"13k","symbolsTime":"12 mins."},"categories":[{"name":"NETWORK","slug":"NETWORK","count":3,"path":"api/categories/NETWORK.json"}],"tags":[],"author":{"name":"dandeliono","slug":"blog-author","avatar":"https://avatars.githubusercontent.com/u/29496357","link":"/","description":"永远相信美好的事情即将发生","socials":{"github":"https://github.com/dandeliono","twitter":"","stackoverflow":"","wechat":"","qq":"","weibo":"","zhihu":"","csdn":"","juejin":"","customs":{}}}},{"title":"直观感受 TLS 握手流程(上)","uid":"18647109cd1271b82271b0b5bf74c52c","slug":"NETWORK/直观感受 TLS 握手流程(上)","date":"2025-08-08T16:59:34.000Z","updated":"2025-08-08T09:17:14.089Z","comments":true,"path":"api/articles/NETWORK/直观感受 TLS 握手流程(上).json","keywords":"XuGuangSheng","cover":[],"text":"直观感受 TLS 握手流程(上)在 HTTPS 开篇的文章中，笔者分析了 HTTPS 之所以安全的原因是因为 TLS 协议的存在。TLS 能保证信息安全和完整性...","permalink":"/post/NETWORK/直观感受 TLS 握手流程(上)","photos":[],"count_time":{"symbolsCount":"56k","symbolsTime":"51 mins."},"categories":[{"name":"NETWORK","slug":"NETWORK","count":3,"path":"api/categories/NETWORK.json"}],"tags":[],"author":{"name":"dandeliono","slug":"blog-author","avatar":"https://avatars.githubusercontent.com/u/29496357","link":"/","description":"永远相信美好的事情即将发生","socials":{"github":"https://github.com/dandeliono","twitter":"","stackoverflow":"","wechat":"","qq":"","weibo":"","zhihu":"","csdn":"","juejin":"","customs":{}}}},{"title":"直观感受 TLS 握手流程(下)","uid":"6097fb5f130a2c4c51fe513482d1af88","slug":"NETWORK/直观感受 TLS 握手流程(下)","date":"2025-08-08T16:59:34.000Z","updated":"2025-08-08T09:17:14.105Z","comments":true,"path":"api/articles/NETWORK/直观感受 TLS 握手流程(下).json","keywords":"XuGuangSheng","cover":[],"text":"直观感受 TLS 握手流程(下)在 HTTPS 开篇的文章中，笔者分析了 HTTPS 之所以安全的原因是因为 TLS 协议的存在。TLS 能保证信息安全和完整性...","permalink":"/post/NETWORK/直观感受 TLS 握手流程(下)","photos":[],"count_time":{"symbolsCount":"44k","symbolsTime":"40 mins."},"categories":[{"name":"NETWORK","slug":"NETWORK","count":3,"path":"api/categories/NETWORK.json"}],"tags":[],"author":{"name":"dandeliono","slug":"blog-author","avatar":"https://avatars.githubusercontent.com/u/29496357","link":"/","description":"永远相信美好的事情即将发生","socials":{"github":"https://github.com/dandeliono","twitter":"","stackoverflow":"","wechat":"","qq":"","weibo":"","zhihu":"","csdn":"","juejin":"","customs":{}}}},{"title":"Docker 镜像一定要瘦身成功！","uid":"36b3336ca3e4df2e2f8cc5b82199f426","slug":"OCI/Docker 镜像一定要瘦身成功！","date":"2025-08-08T16:59:34.000Z","updated":"2025-08-08T09:17:14.752Z","comments":true,"path":"api/articles/OCI/Docker 镜像一定要瘦身成功！.json","keywords":"XuGuangSheng","cover":[],"text":"Docker 镜像一定要瘦身成功！# 简介容器镜像类似于虚拟机镜像，封装了程序的运行环境，保证了运行环境的一致性，使得我们可以一次创建任意场景部署运行。镜像构建...","permalink":"/post/OCI/Docker 镜像一定要瘦身成功！","photos":[],"count_time":{"symbolsCount":"4.8k","symbolsTime":"4 mins."},"categories":[{"name":"OCI","slug":"OCI","count":9,"path":"api/categories/OCI.json"}],"tags":[],"author":{"name":"dandeliono","slug":"blog-author","avatar":"https://avatars.githubusercontent.com/u/29496357","link":"/","description":"永远相信美好的事情即将发生","socials":{"github":"https://github.com/dandeliono","twitter":"","stackoverflow":"","wechat":"","qq":"","weibo":"","zhihu":"","csdn":"","juejin":"","customs":{}}}},{"title":"Longhorn云原生存储","uid":"28da5e689dcfe147ac9028067fa50b4a","slug":"OCI/Longhorn云原生存储","date":"2025-08-08T16:59:34.000Z","updated":"2025-08-08T09:17:14.699Z","comments":true,"path":"api/articles/OCI/Longhorn云原生存储.json","keywords":"XuGuangSheng","cover":[],"text":"Longhorn云原生存储官方github：https://github.com/longhorn/longhorn 官方网站：https://longhorn...","permalink":"/post/OCI/Longhorn云原生存储","photos":[],"count_time":{"symbolsCount":"27k","symbolsTime":"25 mins."},"categories":[{"name":"OCI","slug":"OCI","count":9,"path":"api/categories/OCI.json"}],"tags":[],"author":{"name":"dandeliono","slug":"blog-author","avatar":"https://avatars.githubusercontent.com/u/29496357","link":"/","description":"永远相信美好的事情即将发生","socials":{"github":"https://github.com/dandeliono","twitter":"","stackoverflow":"","wechat":"","qq":"","weibo":"","zhihu":"","csdn":"","juejin":"","customs":{}}}},{"title":"docker-compose部署flink集群","uid":"96cd93f7633628e16d6fdcc58320aac4","slug":"OCI/docker-compose部署flink集群","date":"2025-08-08T16:59:34.000Z","updated":"2025-08-08T09:17:14.738Z","comments":true,"path":"api/articles/OCI/docker-compose部署flink集群.json","keywords":"XuGuangSheng","cover":null,"text":"docker-compose部署flink集群flink 集群部署 拉取 flink 镜像 12docker pull flink 自定义创建目录（例如 / u...","permalink":"/post/OCI/docker-compose部署flink集群","photos":[],"count_time":{"symbolsCount":"12k","symbolsTime":"11 mins."},"categories":[{"name":"OCI","slug":"OCI","count":9,"path":"api/categories/OCI.json"}],"tags":[],"author":{"name":"dandeliono","slug":"blog-author","avatar":"https://avatars.githubusercontent.com/u/29496357","link":"/","description":"永远相信美好的事情即将发生","socials":{"github":"https://github.com/dandeliono","twitter":"","stackoverflow":"","wechat":"","qq":"","weibo":"","zhihu":"","csdn":"","juejin":"","customs":{}}}},{"title":"docker容器内执行linux的dmidecode命令","uid":"c699c53537948b0233bf4a3c00fbe8ed","slug":"OCI/docker容器内执行linux的dmidecode命令","date":"2025-08-08T16:59:34.000Z","updated":"2025-08-08T09:17:14.684Z","comments":true,"path":"api/articles/OCI/docker容器内执行linux的dmidecode命令.json","keywords":"XuGuangSheng","cover":[],"text":"docker容器内执行linux的dmidecode命令报错：[Errno 2] No such file or directory: ‘dmidecode’:...","permalink":"/post/OCI/docker容器内执行linux的dmidecode命令","photos":[],"count_time":{"symbolsCount":525,"symbolsTime":"1 mins."},"categories":[{"name":"OCI","slug":"OCI","count":9,"path":"api/categories/OCI.json"}],"tags":[],"author":{"name":"dandeliono","slug":"blog-author","avatar":"https://avatars.githubusercontent.com/u/29496357","link":"/","description":"永远相信美好的事情即将发生","socials":{"github":"https://github.com/dandeliono","twitter":"","stackoverflow":"","wechat":"","qq":"","weibo":"","zhihu":"","csdn":"","juejin":"","customs":{}}}},{"title":"k8s部署springboot的demo项目","uid":"9a9dc15a004def10ae461436e34e9bad","slug":"OCI/k8s部署springboot的demo项目","date":"2025-08-08T16:59:34.000Z","updated":"2025-08-08T09:17:14.725Z","comments":true,"path":"api/articles/OCI/k8s部署springboot的demo项目.json","keywords":"XuGuangSheng","cover":[],"text":"k8s部署springboot的demo项目1 准备jar包1.1 把你的springboot项目打包成可执行jar包 1.2 把jar包上传到Linux服务器...","permalink":"/post/OCI/k8s部署springboot的demo项目","photos":[],"count_time":{"symbolsCount":"2.9k","symbolsTime":"3 mins."},"categories":[{"name":"OCI","slug":"OCI","count":9,"path":"api/categories/OCI.json"}],"tags":[],"author":{"name":"dandeliono","slug":"blog-author","avatar":"https://avatars.githubusercontent.com/u/29496357","link":"/","description":"永远相信美好的事情即将发生","socials":{"github":"https://github.com/dandeliono","twitter":"","stackoverflow":"","wechat":"","qq":"","weibo":"","zhihu":"","csdn":"","juejin":"","customs":{}}}}]}