{"total":158,"pageSize":12,"pageCount":14,"data":[{"title":"用纯CPU环境搭建大模型环境","uid":"889ca5b7a321750970fca61562d5cfb3","slug":"用纯CPU环境搭建大模型环境","date":"2024-03-05T09:40:56.000Z","updated":"2024-07-11T01:28:38.529Z","comments":true,"path":"api/articles/用纯CPU环境搭建大模型环境.json","keywords":"XuGuangSheng","cover":[],"text":"用纯CPU环境搭建大模型环境配套视频： 大模型现在正处于高速发展时期，各厂商都推出了自己的大模型，各种开源模型也层出不穷。尽管各厂商都有应用接入 API，但在使...","permalink":"/post/用纯CPU环境搭建大模型环境","photos":[],"count_time":{"symbolsCount":"11k","symbolsTime":"10 mins."},"categories":[],"tags":[],"author":{"name":"dandeliono","slug":"blog-author","avatar":"https://avatars.githubusercontent.com/u/29496357","link":"/","description":"永远相信美好的事情即将发生","socials":{"github":"https://github.com/dandeliono","twitter":"","stackoverflow":"","wechat":"","qq":"","weibo":"","zhihu":"","csdn":"","juejin":"","customs":{}}}},{"title":"NullPointerException 没有打印异常栈问题追踪","uid":"f3f0b4e51e77515a8031a4140316d20f","slug":"NullPointerException 没有打印异常栈问题追踪","date":"2024-01-31T16:27:01.000Z","updated":"2024-07-11T01:28:39.397Z","comments":true,"path":"api/articles/NullPointerException 没有打印异常栈问题追踪.json","keywords":"XuGuangSheng","cover":null,"text":"NullPointerException 没有打印异常栈问题追踪今天去服务器后台看日志，发现有很多NullPointerException异常。我下意识的去找异...","permalink":"/post/NullPointerException 没有打印异常栈问题追踪","photos":[],"count_time":{"symbolsCount":"1.3k","symbolsTime":"1 mins."},"categories":[],"tags":[],"author":{"name":"dandeliono","slug":"blog-author","avatar":"https://avatars.githubusercontent.com/u/29496357","link":"/","description":"永远相信美好的事情即将发生","socials":{"github":"https://github.com/dandeliono","twitter":"","stackoverflow":"","wechat":"","qq":"","weibo":"","zhihu":"","csdn":"","juejin":"","customs":{}}}},{"title":"如何在 Docker 容器中使用 systemctl","uid":"cf58df7d33c8bd4e506c71804d861dcc","slug":"如何在 Docker 容器中使用 systemctl","date":"2024-01-29T14:59:56.000Z","updated":"2024-07-11T01:28:40.141Z","comments":true,"path":"api/articles/如何在 Docker 容器中使用 systemctl.json","keywords":"XuGuangSheng","cover":null,"text":"如何在 Docker 容器中使用 systemctl我们有时在使用 docker 的时候，会发现在容器中使用 systemctl 或者 service 的时候，...","permalink":"/post/如何在 Docker 容器中使用 systemctl","photos":[],"count_time":{"symbolsCount":"4.1k","symbolsTime":"4 mins."},"categories":[],"tags":[],"author":{"name":"dandeliono","slug":"blog-author","avatar":"https://avatars.githubusercontent.com/u/29496357","link":"/","description":"永远相信美好的事情即将发生","socials":{"github":"https://github.com/dandeliono","twitter":"","stackoverflow":"","wechat":"","qq":"","weibo":"","zhihu":"","csdn":"","juejin":"","customs":{}}}},{"title":"linux TOP命令各参数详解","uid":"c4719cbd659f86d7d7d8c9fcfcd72c3e","slug":"linux TOP命令各参数详解","date":"2024-01-18T11:57:19.000Z","updated":"2024-07-11T01:28:38.333Z","comments":true,"path":"api/articles/linux TOP命令各参数详解.json","keywords":"XuGuangSheng","cover":[],"text":"linux TOP命令各参数详解[toc] TOP是一个动态显示过程,即可以通过用户按键来不断刷新当前状态.如果在前台执行该命令,它将独占前台,直到用户终止该程...","permalink":"/post/linux TOP命令各参数详解","photos":[],"count_time":{"symbolsCount":"3k","symbolsTime":"3 mins."},"categories":[],"tags":[],"author":{"name":"dandeliono","slug":"blog-author","avatar":"https://avatars.githubusercontent.com/u/29496357","link":"/","description":"永远相信美好的事情即将发生","socials":{"github":"https://github.com/dandeliono","twitter":"","stackoverflow":"","wechat":"","qq":"","weibo":"","zhihu":"","csdn":"","juejin":"","customs":{}}}},{"title":"Elasticsearch中如何进行日期(数值)范围查询","uid":"4bd9e9434ed4ab6b72d76312de1a0204","slug":"Elasticsearch中如何进行日期(数值)范围查询","date":"2024-01-09T13:56:38.000Z","updated":"2024-07-11T01:28:40.817Z","comments":true,"path":"api/articles/Elasticsearch中如何进行日期(数值)范围查询.json","keywords":"XuGuangSheng","cover":null,"text":"Elasticsearch中如何进行日期(数值)范围查询 符号 含义 gte greater-than or equal to, 大于或等于 gt greate...","permalink":"/post/Elasticsearch中如何进行日期(数值)范围查询","photos":[],"count_time":{"symbolsCount":"3k","symbolsTime":"3 mins."},"categories":[],"tags":[],"author":{"name":"dandeliono","slug":"blog-author","avatar":"https://avatars.githubusercontent.com/u/29496357","link":"/","description":"永远相信美好的事情即将发生","socials":{"github":"https://github.com/dandeliono","twitter":"","stackoverflow":"","wechat":"","qq":"","weibo":"","zhihu":"","csdn":"","juejin":"","customs":{}}}},{"title":"ElasticSearch里面如何分组后根据sum值排序","uid":"4483f94e0db17009da0543d6cde026da","slug":"ElasticSearch里面如何分组后根据sum值排序","date":"2024-01-09T13:55:15.000Z","updated":"2024-07-11T01:28:40.541Z","comments":true,"path":"api/articles/ElasticSearch里面如何分组后根据sum值排序.json","keywords":"XuGuangSheng","cover":null,"text":"ElasticSearch里面如何分组后根据sum值排序ElasticSearch里面的聚合机制非常灵活和强大，今天我们来看下如何在ElasticSearch里...","permalink":"/post/ElasticSearch里面如何分组后根据sum值排序","photos":[],"count_time":{"symbolsCount":"1.6k","symbolsTime":"1 mins."},"categories":[],"tags":[],"author":{"name":"dandeliono","slug":"blog-author","avatar":"https://avatars.githubusercontent.com/u/29496357","link":"/","description":"永远相信美好的事情即将发生","socials":{"github":"https://github.com/dandeliono","twitter":"","stackoverflow":"","wechat":"","qq":"","weibo":"","zhihu":"","csdn":"","juejin":"","customs":{}}}},{"title":"使用 libfaketime 修改 docker 容器时间","uid":"9c243b726e495059eca1f4eed1c4f935","slug":"使用 libfaketime 修改 docker 容器时间","date":"2023-12-14T14:07:31.000Z","updated":"2024-07-11T01:28:40.645Z","comments":true,"path":"api/articles/使用 libfaketime 修改 docker 容器时间.json","keywords":"XuGuangSheng","cover":null,"text":"使用 libfaketime 修改 docker 容器时间容器的时间问题：如果想要直接进入容器，使用date -s修改日期，则会出现一个 1 的错误，而且也不会...","permalink":"/post/使用 libfaketime 修改 docker 容器时间","photos":[],"count_time":{"symbolsCount":"1.6k","symbolsTime":"1 mins."},"categories":[],"tags":[],"author":{"name":"dandeliono","slug":"blog-author","avatar":"https://avatars.githubusercontent.com/u/29496357","link":"/","description":"永远相信美好的事情即将发生","socials":{"github":"https://github.com/dandeliono","twitter":"","stackoverflow":"","wechat":"","qq":"","weibo":"","zhihu":"","csdn":"","juejin":"","customs":{}}}},{"title":"Linux 系统监控工具 atop","uid":"82b3a52976f247e94d00aebe443d97b1","slug":"Linux 系统监控工具 atop","date":"2023-12-13T09:25:22.000Z","updated":"2024-07-11T01:28:38.505Z","comments":true,"path":"api/articles/Linux 系统监控工具 atop.json","keywords":"XuGuangSheng","cover":[],"text":"Linux 系统监控工具 atop系统监控是运维工作中重要的一环，本文以 atop 工具为例来介绍系统的重要监控项。 atop可以使用yum或apt包管理器进行...","permalink":"/post/Linux 系统监控工具 atop","photos":[],"count_time":{"symbolsCount":"4.9k","symbolsTime":"4 mins."},"categories":[],"tags":[],"author":{"name":"dandeliono","slug":"blog-author","avatar":"https://avatars.githubusercontent.com/u/29496357","link":"/","description":"永远相信美好的事情即将发生","socials":{"github":"https://github.com/dandeliono","twitter":"","stackoverflow":"","wechat":"","qq":"","weibo":"","zhihu":"","csdn":"","juejin":"","customs":{}}}},{"title":"使用prlimit命令不重启进程修改其limits等运行参数","uid":"57ca05a26664334bc519d817eff06219","slug":"使用prlimit命令不重启进程修改其limits等运行参数","date":"2023-11-29T14:25:53.000Z","updated":"2024-07-11T01:28:40.477Z","comments":true,"path":"api/articles/使用prlimit命令不重启进程修改其limits等运行参数.json","keywords":"XuGuangSheng","cover":null,"text":"使用prlimit命令不重启进程修改其limits等运行参数12345678910111213141516171819202122232425262728293...","permalink":"/post/使用prlimit命令不重启进程修改其limits等运行参数","photos":[],"count_time":{"symbolsCount":"3k","symbolsTime":"3 mins."},"categories":[],"tags":[],"author":{"name":"dandeliono","slug":"blog-author","avatar":"https://avatars.githubusercontent.com/u/29496357","link":"/","description":"永远相信美好的事情即将发生","socials":{"github":"https://github.com/dandeliono","twitter":"","stackoverflow":"","wechat":"","qq":"","weibo":"","zhihu":"","csdn":"","juejin":"","customs":{}}}},{"title":"Elasticsearch 数值类型也能存String 类型问题分析","uid":"e31577451631f8a2adc07bcea9f94111","slug":"Elasticsearch 数值类型也能存String 类型问题分析","date":"2023-11-22T10:47:50.000Z","updated":"2024-07-11T01:28:38.981Z","comments":true,"path":"api/articles/Elasticsearch 数值类型也能存String 类型问题分析.json","keywords":"XuGuangSheng","cover":[],"text":"Elasticsearch 数值类型也能存String 类型问题分析最近经常遇到遇到某个客户问数值类型的字段也能存字符串，或者说已经将字段类型设置成了float...","permalink":"/post/Elasticsearch 数值类型也能存String 类型问题分析","photos":[],"count_time":{"symbolsCount":"3.7k","symbolsTime":"3 mins."},"categories":[],"tags":[],"author":{"name":"dandeliono","slug":"blog-author","avatar":"https://avatars.githubusercontent.com/u/29496357","link":"/","description":"永远相信美好的事情即将发生","socials":{"github":"https://github.com/dandeliono","twitter":"","stackoverflow":"","wechat":"","qq":"","weibo":"","zhihu":"","csdn":"","juejin":"","customs":{}}}},{"title":"从 apache-common-pool 看如何写一个通用池","uid":"a3ec52c6805d10835480c023a68f988e","slug":"从 apache-common-pool 看如何写一个通用池","date":"2023-11-16T11:44:17.000Z","updated":"2024-07-11T01:28:38.853Z","comments":true,"path":"api/articles/从 apache-common-pool 看如何写一个通用池.json","keywords":"XuGuangSheng","cover":[],"text":"从 apache-common-pool 看如何写一个通用池对象的创建和销毁在一定程度上会消耗系统的资源，虽然 jvm 的性能在近几年已经得到了很大的提高，对于...","permalink":"/post/从 apache-common-pool 看如何写一个通用池","photos":[],"count_time":{"symbolsCount":"28k","symbolsTime":"25 mins."},"categories":[],"tags":[],"author":{"name":"dandeliono","slug":"blog-author","avatar":"https://avatars.githubusercontent.com/u/29496357","link":"/","description":"永远相信美好的事情即将发生","socials":{"github":"https://github.com/dandeliono","twitter":"","stackoverflow":"","wechat":"","qq":"","weibo":"","zhihu":"","csdn":"","juejin":"","customs":{}}}},{"title":"SpringBoot 扩展接口","uid":"b17fc263eaa274b6bfcba03d60c157eb","slug":"SpringBoot 扩展接口","date":"2023-11-15T16:23:04.000Z","updated":"2024-07-11T01:28:39.185Z","comments":true,"path":"api/articles/SpringBoot 扩展接口.json","keywords":"XuGuangSheng","cover":[],"text":"SpringBoot 扩展接口1、背景Spring的核心思想就是容器，当容器refresh的时候，外部看上去风平浪静，其实内部则是一片惊涛骇浪，汪洋一片。Spr...","permalink":"/post/SpringBoot 扩展接口","photos":[],"count_time":{"symbolsCount":"15k","symbolsTime":"13 mins."},"categories":[],"tags":[],"author":{"name":"dandeliono","slug":"blog-author","avatar":"https://avatars.githubusercontent.com/u/29496357","link":"/","description":"永远相信美好的事情即将发生","socials":{"github":"https://github.com/dandeliono","twitter":"","stackoverflow":"","wechat":"","qq":"","weibo":"","zhihu":"","csdn":"","juejin":"","customs":{}}}}]}